{
  "auth": {
    "user_pool_id": "us-east-1_lZ3nqAZvG",
    "aws_region": "us-east-1",
    "user_pool_client_id": "6d1anpptvjdu8bqeqp1um7p16h",
    "identity_pool_id": "us-east-1:8021bf9b-73c6-4304-b036-85e5e440afa5",
    "mfa_methods": [],
    "standard_required_attributes": [
      "email"
    ],
    "username_attributes": [
      "email"
    ],
    "user_verification_types": [
      "email"
    ],
    "groups": [],
    "mfa_configuration": "NONE",
    "password_policy": {
      "min_length": 8,
      "require_lowercase": true,
      "require_numbers": true,
      "require_symbols": true,
      "require_uppercase": true
    },
    "unauthenticated_identities_enabled": true
  },
  "data": {
    "url": "https://46rlxyesdjgghddr5haubgmyly.appsync-api.us-east-1.amazonaws.com/graphql",
    "aws_region": "us-east-1",
    "api_key": "da2-lyxgs7ya7zakdjrn7bxumrwxcy",
    "default_authorization_type": "API_KEY",
    "authorization_types": [
      "AMAZON_COGNITO_USER_POOLS",
      "AWS_IAM"
    ],
    "model_introspection": {
      "version": 1,
      "models": {
        "Load": {
          "name": "Load",
          "fields": {
            "id": {
              "name": "id",
              "isArray": false,
              "type": "ID",
              "isRequired": true,
              "attributes": []
            },
            "storeNumber": {
              "name": "storeNumber",
              "isArray": false,
              "type": "String",
              "isRequired": true,
              "attributes": []
            },
            "dispatchDate": {
              "name": "dispatchDate",
              "isArray": false,
              "type": "String",
              "isRequired": true,
              "attributes": []
            },
            "dispatchWindow": {
              "name": "dispatchWindow",
              "isArray": false,
              "type": "String",
              "isRequired": true,
              "attributes": []
            },
            "activityType": {
              "name": "activityType",
              "isArray": false,
              "type": "String",
              "isRequired": true,
              "attributes": []
            },
            "equipmentType": {
              "name": "equipmentType",
              "isArray": false,
              "type": "String",
              "isRequired": false,
              "attributes": []
            },
            "brokerName": {
              "name": "brokerName",
              "isArray": false,
              "type": "String",
              "isRequired": false,
              "attributes": []
            },
            "carrierName": {
              "name": "carrierName",
              "isArray": false,
              "type": "String",
              "isRequired": false,
              "attributes": []
            },
            "tripId": {
              "name": "tripId",
              "isArray": false,
              "type": "String",
              "isRequired": false,
              "attributes": []
            },
            "rate": {
              "name": "rate",
              "isArray": false,
              "type": "Float",
              "isRequired": false,
              "attributes": []
            },
            "status": {
              "name": "status",
              "isArray": false,
              "type": "String",
              "isRequired": true,
              "attributes": []
            },
            "bolStatus": {
              "name": "bolStatus",
              "isArray": false,
              "type": "String",
              "isRequired": false,
              "attributes": []
            },
            "createdBy": {
              "name": "createdBy",
              "isArray": false,
              "type": "String",
              "isRequired": false,
              "attributes": []
            },
            "notes": {
              "name": "notes",
              "isArray": false,
              "type": "String",
              "isRequired": false,
              "attributes": []
            },
            "createdAt": {
              "name": "createdAt",
              "isArray": false,
              "type": "AWSDateTime",
              "isRequired": false,
              "attributes": [],
              "isReadOnly": true
            },
            "updatedAt": {
              "name": "updatedAt",
              "isArray": false,
              "type": "AWSDateTime",
              "isRequired": false,
              "attributes": [],
              "isReadOnly": true
            }
          },
          "syncable": true,
          "pluralName": "Loads",
          "attributes": [
            {
              "type": "model",
              "properties": {}
            },
            {
              "type": "auth",
              "properties": {
                "rules": [
                  {
                    "allow": "public",
                    "provider": "apiKey",
                    "operations": [
                      "create",
                      "update",
                      "delete",
                      "read"
                    ]
                  }
                ]
              }
            }
          ],
          "primaryKeyInfo": {
            "isCustomPrimaryKey": false,
            "primaryKeyFieldName": "id",
            "sortKeyFieldNames": []
          }
        },
        "DispatchWindow": {
          "name": "DispatchWindow",
          "fields": {
            "id": {
              "name": "id",
              "isArray": false,
              "type": "ID",
              "isRequired": true,
              "attributes": []
            },
            "dispatchDate": {
              "name": "dispatchDate",
              "isArray": false,
              "type": "String",
              "isRequired": true,
              "attributes": []
            },
            "dispatchTime": {
              "name": "dispatchTime",
              "isArray": false,
              "type": "String",
              "isRequired": true,
              "attributes": []
            },
            "brokerName": {
              "name": "brokerName",
              "isArray": false,
              "type": "String",
              "isRequired": false,
              "attributes": []
            },
            "loadCount": {
              "name": "loadCount",
              "isArray": false,
              "type": "Int",
              "isRequired": false,
              "attributes": []
            },
            "status": {
              "name": "status",
              "isArray": false,
              "type": "String",
              "isRequired": true,
              "attributes": []
            },
            "createdAt": {
              "name": "createdAt",
              "isArray": false,
              "type": "AWSDateTime",
              "isRequired": false,
              "attributes": [],
              "isReadOnly": true
            },
            "updatedAt": {
              "name": "updatedAt",
              "isArray": false,
              "type": "AWSDateTime",
              "isRequired": false,
              "attributes": [],
              "isReadOnly": true
            }
          },
          "syncable": true,
          "pluralName": "DispatchWindows",
          "attributes": [
            {
              "type": "model",
              "properties": {}
            },
            {
              "type": "auth",
              "properties": {
                "rules": [
                  {
                    "allow": "public",
                    "provider": "apiKey",
                    "operations": [
                      "create",
                      "update",
                      "delete",
                      "read"
                    ]
                  }
                ]
              }
            }
          ],
          "primaryKeyInfo": {
            "isCustomPrimaryKey": false,
            "primaryKeyFieldName": "id",
            "sortKeyFieldNames": []
          }
        },
        "Trip": {
          "name": "Trip",
          "fields": {
            "id": {
              "name": "id",
              "isArray": false,
              "type": "ID",
              "isRequired": true,
              "attributes": []
            },
            "tripId": {
              "name": "tripId",
              "isArray": false,
              "type": "String",
              "isRequired": true,
              "attributes": []
            },
            "loadId": {
              "name": "loadId",
              "isArray": false,
              "type": "String",
              "isRequired": true,
              "attributes": []
            },
            "carrierName": {
              "name": "carrierName",
              "isArray": false,
              "type": "String",
              "isRequired": false,
              "attributes": []
            },
            "driverName": {
              "name": "driverName",
              "isArray": false,
              "type": "String",
              "isRequired": false,
              "attributes": []
            },
            "trailerNumber": {
              "name": "trailerNumber",
              "isArray": false,
              "type": "String",
              "isRequired": false,
              "attributes": []
            },
            "doorNumber": {
              "name": "doorNumber",
              "isArray": false,
              "type": "String",
              "isRequired": false,
              "attributes": []
            },
            "status": {
              "name": "status",
              "isArray": false,
              "type": "String",
              "isRequired": true,
              "attributes": []
            },
            "createdAt": {
              "name": "createdAt",
              "isArray": false,
              "type": "AWSDateTime",
              "isRequired": false,
              "attributes": [],
              "isReadOnly": true
            },
            "updatedAt": {
              "name": "updatedAt",
              "isArray": false,
              "type": "AWSDateTime",
              "isRequired": false,
              "attributes": [],
              "isReadOnly": true
            }
          },
          "syncable": true,
          "pluralName": "Trips",
          "attributes": [
            {
              "type": "model",
              "properties": {}
            },
            {
              "type": "auth",
              "properties": {
                "rules": [
                  {
                    "allow": "public",
                    "provider": "apiKey",
                    "operations": [
                      "create",
                      "update",
                      "delete",
                      "read"
                    ]
                  }
                ]
              }
            }
          ],
          "primaryKeyInfo": {
            "isCustomPrimaryKey": false,
            "primaryKeyFieldName": "id",
            "sortKeyFieldNames": []
          }
        },
        "LoadEvent": {
          "name": "LoadEvent",
          "fields": {
            "id": {
              "name": "id",
              "isArray": false,
              "type": "ID",
              "isRequired": true,
              "attributes": []
            },
            "loadId": {
              "name": "loadId",
              "isArray": false,
              "type": "String",
              "isRequired": true,
              "attributes": []
            },
            "eventType": {
              "name": "eventType",
              "isArray": false,
              "type": "String",
              "isRequired": true,
              "attributes": []
            },
            "eventTime": {
              "name": "eventTime",
              "isArray": false,
              "type": "String",
              "isRequired": true,
              "attributes": []
            },
            "eventSource": {
              "name": "eventSource",
              "isArray": false,
              "type": "String",
              "isRequired": false,
              "attributes": []
            },
            "userId": {
              "name": "userId",
              "isArray": false,
              "type": "String",
              "isRequired": false,
              "attributes": []
            },
            "notes": {
              "name": "notes",
              "isArray": false,
              "type": "String",
              "isRequired": false,
              "attributes": []
            },
            "delayPhase": {
              "name": "delayPhase",
              "isArray": false,
              "type": "String",
              "isRequired": false,
              "attributes": []
            },
            "delayReason": {
              "name": "delayReason",
              "isArray": false,
              "type": "String",
              "isRequired": false,
              "attributes": []
            },
            "delayMinutes": {
              "name": "delayMinutes",
              "isArray": false,
              "type": "Int",
              "isRequired": false,
              "attributes": []
            },
            "updatedEta": {
              "name": "updatedEta",
              "isArray": false,
              "type": "String",
              "isRequired": false,
              "attributes": []
            },
            "dockNumber": {
              "name": "dockNumber",
              "isArray": false,
              "type": "String",
              "isRequired": false,
              "attributes": []
            },
            "trailerNumber": {
              "name": "trailerNumber",
              "isArray": false,
              "type": "String",
              "isRequired": false,
              "attributes": []
            },
            "latitude": {
              "name": "latitude",
              "isArray": false,
              "type": "Float",
              "isRequired": false,
              "attributes": []
            },
            "longitude": {
              "name": "longitude",
              "isArray": false,
              "type": "Float",
              "isRequired": false,
              "attributes": []
            },
            "createdAt": {
              "name": "createdAt",
              "isArray": false,
              "type": "AWSDateTime",
              "isRequired": false,
              "attributes": [],
              "isReadOnly": true
            },
            "updatedAt": {
              "name": "updatedAt",
              "isArray": false,
              "type": "AWSDateTime",
              "isRequired": false,
              "attributes": [],
              "isReadOnly": true
            }
          },
          "syncable": true,
          "pluralName": "LoadEvents",
          "attributes": [
            {
              "type": "model",
              "properties": {}
            },
            {
              "type": "auth",
              "properties": {
                "rules": [
                  {
                    "allow": "public",
                    "provider": "apiKey",
                    "operations": [
                      "create",
                      "update",
                      "delete",
                      "read"
                    ]
                  }
                ]
              }
            }
          ],
          "primaryKeyInfo": {
            "isCustomPrimaryKey": false,
            "primaryKeyFieldName": "id",
            "sortKeyFieldNames": []
          }
        },
        "Notification": {
          "name": "Notification",
          "fields": {
            "id": {
              "name": "id",
              "isArray": false,
              "type": "ID",
              "isRequired": true,
              "attributes": []
            },
            "loadId": {
              "name": "loadId",
              "isArray": false,
              "type": "String",
              "isRequired": false,
              "attributes": []
            },
            "eventType": {
              "name": "eventType",
              "isArray": false,
              "type": "String",
              "isRequired": true,
              "attributes": []
            },
            "audience": {
              "name": "audience",
              "isArray": false,
              "type": "String",
              "isRequired": true,
              "attributes": []
            },
            "title": {
              "name": "title",
              "isArray": false,
              "type": "String",
              "isRequired": true,
              "attributes": []
            },
            "message": {
              "name": "message",
              "isArray": false,
              "type": "String",
              "isRequired": true,
              "attributes": []
            },
            "channel": {
              "name": "channel",
              "isArray": false,
              "type": "String",
              "isRequired": true,
              "attributes": []
            },
            "status": {
              "name": "status",
              "isArray": false,
              "type": "String",
              "isRequired": true,
              "attributes": []
            },
            "createdAt": {
              "name": "createdAt",
              "isArray": false,
              "type": "String",
              "isRequired": true,
              "attributes": []
            },
            "readAt": {
              "name": "readAt",
              "isArray": false,
              "type": "String",
              "isRequired": false,
              "attributes": []
            },
            "updatedAt": {
              "name": "updatedAt",
              "isArray": false,
              "type": "AWSDateTime",
              "isRequired": false,
              "attributes": [],
              "isReadOnly": true
            }
          },
          "syncable": true,
          "pluralName": "Notifications",
          "attributes": [
            {
              "type": "model",
              "properties": {}
            },
            {
              "type": "auth",
              "properties": {
                "rules": [
                  {
                    "allow": "public",
                    "provider": "apiKey",
                    "operations": [
                      "create",
                      "update",
                      "delete",
                      "read"
                    ]
                  }
                ]
              }
            }
          ],
          "primaryKeyInfo": {
            "isCustomPrimaryKey": false,
            "primaryKeyFieldName": "id",
            "sortKeyFieldNames": []
          }
        },
        "LoadException": {
          "name": "LoadException",
          "fields": {
            "id": {
              "name": "id",
              "isArray": false,
              "type": "ID",
              "isRequired": true,
              "attributes": []
            },
            "loadId": {
              "name": "loadId",
              "isArray": false,
              "type": "String",
              "isRequired": true,
              "attributes": []
            },
            "exceptionType": {
              "name": "exceptionType",
              "isArray": false,
              "type": "String",
              "isRequired": true,
              "attributes": []
            },
            "priority": {
              "name": "priority",
              "isArray": false,
              "type": "String",
              "isRequired": true,
              "attributes": []
            },
            "status": {
              "name": "status",
              "isArray": false,
              "type": "String",
              "isRequired": true,
              "attributes": []
            },
            "delayPhase": {
              "name": "delayPhase",
              "isArray": false,
              "type": "String",
              "isRequired": false,
              "attributes": []
            },
            "etaImpactMinutes": {
              "name": "etaImpactMinutes",
              "isArray": false,
              "type": "Int",
              "isRequired": false,
              "attributes": []
            },
            "notes": {
              "name": "notes",
              "isArray": false,
              "type": "String",
              "isRequired": false,
              "attributes": []
            },
            "createdAt": {
              "name": "createdAt",
              "isArray": false,
              "type": "AWSDateTime",
              "isRequired": false,
              "attributes": [],
              "isReadOnly": true
            },
            "updatedAt": {
              "name": "updatedAt",
              "isArray": false,
              "type": "AWSDateTime",
              "isRequired": false,
              "attributes": [],
              "isReadOnly": true
            }
          },
          "syncable": true,
          "pluralName": "LoadExceptions",
          "attributes": [
            {
              "type": "model",
              "properties": {}
            },
            {
              "type": "auth",
              "properties": {
                "rules": [
                  {
                    "allow": "public",
                    "provider": "apiKey",
                    "operations": [
                      "create",
                      "update",
                      "delete",
                      "read"
                    ]
                  }
                ]
              }
            }
          ],
          "primaryKeyInfo": {
            "isCustomPrimaryKey": false,
            "primaryKeyFieldName": "id",
            "sortKeyFieldNames": []
          }
        },
        "Broker": {
          "name": "Broker",
          "fields": {
            "id": {
              "name": "id",
              "isArray": false,
              "type": "ID",
              "isRequired": true,
              "attributes": []
            },
            "brokerName": {
              "name": "brokerName",
              "isArray": false,
              "type": "String",
              "isRequired": true,
              "attributes": []
            },
            "contactName": {
              "name": "contactName",
              "isArray": false,
              "type": "String",
              "isRequired": false,
              "attributes": []
            },
            "email": {
              "name": "email",
              "isArray": false,
              "type": "String",
              "isRequired": false,
              "attributes": []
            },
            "status": {
              "name": "status",
              "isArray": false,
              "type": "String",
              "isRequired": false,
              "attributes": []
            },
            "createdAt": {
              "name": "createdAt",
              "isArray": false,
              "type": "AWSDateTime",
              "isRequired": false,
              "attributes": [],
              "isReadOnly": true
            },
            "updatedAt": {
              "name": "updatedAt",
              "isArray": false,
              "type": "AWSDateTime",
              "isRequired": false,
              "attributes": [],
              "isReadOnly": true
            }
          },
          "syncable": true,
          "pluralName": "Brokers",
          "attributes": [
            {
              "type": "model",
              "properties": {}
            },
            {
              "type": "auth",
              "properties": {
                "rules": [
                  {
                    "allow": "public",
                    "provider": "apiKey",
                    "operations": [
                      "create",
                      "update",
                      "delete",
                      "read"
                    ]
                  }
                ]
              }
            }
          ],
          "primaryKeyInfo": {
            "isCustomPrimaryKey": false,
            "primaryKeyFieldName": "id",
            "sortKeyFieldNames": []
          }
        },
        "Carrier": {
          "name": "Carrier",
          "fields": {
            "id": {
              "name": "id",
              "isArray": false,
              "type": "ID",
              "isRequired": true,
              "attributes": []
            },
            "carrierName": {
              "name": "carrierName",
              "isArray": false,
              "type": "String",
              "isRequired": true,
              "attributes": []
            },
            "mcNumber": {
              "name": "mcNumber",
              "isArray": false,
              "type": "String",
              "isRequired": false,
              "attributes": []
            },
            "dotNumber": {
              "name": "dotNumber",
              "isArray": false,
              "type": "String",
              "isRequired": false,
              "attributes": []
            },
            "status": {
              "name": "status",
              "isArray": false,
              "type": "String",
              "isRequired": false,
              "attributes": []
            },
            "trackingParticipationRate": {
              "name": "trackingParticipationRate",
              "isArray": false,
              "type": "Float",
              "isRequired": false,
              "attributes": []
            },
            "createdAt": {
              "name": "createdAt",
              "isArray": false,
              "type": "AWSDateTime",
              "isRequired": false,
              "attributes": [],
              "isReadOnly": true
            },
            "updatedAt": {
              "name": "updatedAt",
              "isArray": false,
              "type": "AWSDateTime",
              "isRequired": false,
              "attributes": [],
              "isReadOnly": true
            }
          },
          "syncable": true,
          "pluralName": "Carriers",
          "attributes": [
            {
              "type": "model",
              "properties": {}
            },
            {
              "type": "auth",
              "properties": {
                "rules": [
                  {
                    "allow": "public",
                    "provider": "apiKey",
                    "operations": [
                      "create",
                      "update",
                      "delete",
                      "read"
                    ]
                  }
                ]
              }
            }
          ],
          "primaryKeyInfo": {
            "isCustomPrimaryKey": false,
            "primaryKeyFieldName": "id",
            "sortKeyFieldNames": []
          }
        },
        "Driver": {
          "name": "Driver",
          "fields": {
            "id": {
              "name": "id",
              "isArray": false,
              "type": "ID",
              "isRequired": true,
              "attributes": []
            },
            "carrierId": {
              "name": "carrierId",
              "isArray": false,
              "type": "String",
              "isRequired": true,
              "attributes": []
            },
            "driverName": {
              "name": "driverName",
              "isArray": false,
              "type": "String",
              "isRequired": true,
              "attributes": []
            },
            "phoneNumber": {
              "name": "phoneNumber",
              "isArray": false,
              "type": "String",
              "isRequired": false,
              "attributes": []
            },
            "status": {
              "name": "status",
              "isArray": false,
              "type": "String",
              "isRequired": false,
              "attributes": []
            },
            "createdAt": {
              "name": "createdAt",
              "isArray": false,
              "type": "AWSDateTime",
              "isRequired": false,
              "attributes": [],
              "isReadOnly": true
            },
            "updatedAt": {
              "name": "updatedAt",
              "isArray": false,
              "type": "AWSDateTime",
              "isRequired": false,
              "attributes": [],
              "isReadOnly": true
            }
          },
          "syncable": true,
          "pluralName": "Drivers",
          "attributes": [
            {
              "type": "model",
              "properties": {}
            },
            {
              "type": "auth",
              "properties": {
                "rules": [
                  {
                    "allow": "public",
                    "provider": "apiKey",
                    "operations": [
                      "create",
                      "update",
                      "delete",
                      "read"
                    ]
                  }
                ]
              }
            }
          ],
          "primaryKeyInfo": {
            "isCustomPrimaryKey": false,
            "primaryKeyFieldName": "id",
            "sortKeyFieldNames": []
          }
        },
        "DriverLocation": {
          "name": "DriverLocation",
          "fields": {
            "id": {
              "name": "id",
              "isArray": false,
              "type": "ID",
              "isRequired": true,
              "attributes": []
            },
            "loadId": {
              "name": "loadId",
              "isArray": false,
              "type": "String",
              "isRequired": true,
              "attributes": []
            },
            "driverName": {
              "name": "driverName",
              "isArray": false,
              "type": "String",
              "isRequired": false,
              "attributes": []
            },
            "carrierName": {
              "name": "carrierName",
              "isArray": false,
              "type": "String",
              "isRequired": false,
              "attributes": []
            },
            "latitude": {
              "name": "latitude",
              "isArray": false,
              "type": "Float",
              "isRequired": true,
              "attributes": []
            },
            "longitude": {
              "name": "longitude",
              "isArray": false,
              "type": "Float",
              "isRequired": true,
              "attributes": []
            },
            "recordedAt": {
              "name": "recordedAt",
              "isArray": false,
              "type": "String",
              "isRequired": true,
              "attributes": []
            },
            "source": {
              "name": "source",
              "isArray": false,
              "type": "String",
              "isRequired": false,
              "attributes": []
            },
            "locationMethod": {
              "name": "locationMethod",
              "isArray": false,
              "type": "String",
              "isRequired": false,
              "attributes": []
            },
            "accuracyMeters": {
              "name": "accuracyMeters",
              "isArray": false,
              "type": "Float",
              "isRequired": false,
              "attributes": []
            },
            "notes": {
              "name": "notes",
              "isArray": false,
              "type": "String",
              "isRequired": false,
              "attributes": []
            },
            "createdAt": {
              "name": "createdAt",
              "isArray": false,
              "type": "AWSDateTime",
              "isRequired": false,
              "attributes": [],
              "isReadOnly": true
            },
            "updatedAt": {
              "name": "updatedAt",
              "isArray": false,
              "type": "AWSDateTime",
              "isRequired": false,
              "attributes": [],
              "isReadOnly": true
            }
          },
          "syncable": true,
          "pluralName": "DriverLocations",
          "attributes": [
            {
              "type": "model",
              "properties": {}
            },
            {
              "type": "auth",
              "properties": {
                "rules": [
                  {
                    "allow": "public",
                    "provider": "apiKey",
                    "operations": [
                      "create",
                      "update",
                      "delete",
                      "read"
                    ]
                  }
                ]
              }
            }
          ],
          "primaryKeyInfo": {
            "isCustomPrimaryKey": false,
            "primaryKeyFieldName": "id",
            "sortKeyFieldNames": []
          }
        }
      },
      "enums": {},
      "nonModels": {}
    }
  },
  "version": "1.4"
}